{
    "name": "flare",
    "children": [
        {
            "name": "Topic 1",
            "children": [
                {
                    "name": "register deadline",
                    "size": 8258
                },
                {
                    "name": "food event",
                    "size": 10001
                },
                {
                    "name": "yes",
                    "size": 8217
                },
                {
                    "name": "play",
                    "size": 12555
                },
                {
                    "name": "tour",
                    "size": 2324
                },
                {
                    "name": "stars",
                    "size": 10993
                },
                {
                    "name": "girls",
                    "size": 335
                },
                {
                    "name": "debate sat",
                    "size": 383
                },
                {
                    "name": "please share",
                    "size": 874
                },
                {
                    "name": "law",
                    "size": 17705
                }
   ]
  },
        {
            "name": "Topic 2",
            "children": [
                {
                    "name": "won ireland",
                    "size": 8258
                },
                {
                    "name": "tourism ireland",
                    "size": 10001
                },
                {
                    "name": "sligo see",
                    "size": 8217
                },
                {
                    "name": "event today",
                    "size": 12555
                },
                {
                    "name": "team ireland",
                    "size": 2324
                },
                {
                    "name": "day tomorrow",
                    "size": 10993
                },
                {
                    "name": "sligo get",
                    "size": 335
                },
                {
                    "name": "week yeats",
                    "size": 383
                },
                {
                    "name": "today story",
                    "size": 874
                },
                {
                    "name": "moon sligo",
                    "size": 17705
                }
   ]
  },
        {
            "name": "Topic 3",
            "children": [
                {
                    "name": "poetry reading",
                    "size": 8258
                },
                {
                    "name": "film",
                    "size": 10001
                },
                {
                    "name": "hope everyone",
                    "size": 8217
                },
                {
                    "name": "support ",
                    "size": 12555
                },
                {
                    "name": "youryeats ",
                    "size": 2324
                },
                {
                    "name": "saturday media",
                    "size": 10993
                },
                {
                    "name": "october ",
                    "size": 335
                },
                {
                    "name": "sea friday ",
                    "size": 383
                },
                {
                    "name": "christmas ",
                    "size": 874
                },
                {
                    "name": "country house",
                    "size": 17705
                }
   ]
  },
        {
            "name": "Topic 4",
            "children": [
                {
                    "name": "tomorrow talk ",
                    "size": 8258
                },
                {
                    "name": "life ",
                    "size": 10001
                },
                {
                    "name": "women nollaignamban ",
                    "size": 8217
                },
                {
                    "name": "congrats",
                    "size": 12555
                },
                {
                    "name": "launch",
                    "size": 2324
                },
                {
                    "name": "share evening",
                    "size": 10993
                },
                {
                    "name": "yesterday evening",
                    "size": 335
                },
                {
                    "name": "students tonight ",
                    "size": 383
                },
                {
                    "name": "events thank ",
                    "size": 874
                },
                {
                    "name": "bankinginquiry",
                    "size": 17705
                }
   ]
  },
        {
            "name": "Topic 5",
            "children": [
                {
                    "name": "uk amp ",
                    "size": 8258
                },
                {
                    "name": "enter amp",
                    "size": 10001
                },
                {
                    "name": "walks amp",
                    "size": 8217
                },
                {
                    "name": "design amp",
                    "size": 12555
                },
                {
                    "name": "article amp",
                    "size": 2324
                },
                {
                    "name": "tues amp",
                    "size": 10993
                },
                {
                    "name": "say amp ",
                    "size": 335
                },
                {
                    "name": "health amp ",
                    "size": 383
                },
                {
                    "name": "arrivals amp",
                    "size": 874
                },
                {
                    "name": "netherlands amp ",
                    "size": 17705
                }
   ]
  },
        {
            "name": "Topic 6",
            "children": [
                {
                    "name": "season support ",
                    "size": 8258
                },
                {
                    "name": "president",
                    "size": 10001
                },
                {
                    "name": "lovesligo ",
                    "size": 8217
                },
                {
                    "name": "fleadh",
                    "size": 12555
                },
                {
                    "name": "students",
                    "size": 2324
                },
                {
                    "name": "water ",
                    "size": 10993
                },
                {
                    "name": "mind",
                    "size": 335
                },
                {
                    "name": "poets sat ",
                    "size": 383
                },
                {
                    "name": "design students",
                    "size": 874
                },
                {
                    "name": "kids ",
                    "size": 17705
                }
   ]
  },
        {
            "name": "Topic 7",
            "children": [
                {
                    "name": "amp ",
                    "size": 8258
                },
                {
                    "name": "yeats amp ",
                    "size": 10001
                },
                {
                    "name": "ireland amp ",
                    "size": 8217
                },
                {
                    "name": "today amp ",
                    "size": 12555
                },
                {
                    "name": "sligo amp ",
                    "size": 2324
                },
                {
                    "name": "yeats ",
                    "size": 10993
                },
                {
                    "name": "day amp ",
                    "size": 335
                },
                {
                    "name": "week amp ",
                    "size": 383
                },
                {
                    "name": " women amp",
                    "size": 874
                },
                {
                    "name": "yeats ireland ",
                    "size": 17705
                }
   ]
  },
        {
            "name": "Topic 8",
            "children": [
                {
                    "name": "candidate video ",
                    "size": 8258
                },
                {
                    "name": "centre food ",
                    "size": 10001
                },
                {
                    "name": "yeats",
                    "size": 8217
                },
                {
                    "name": "book awards",
                    "size": 12555
                },
                {
                    "name": "tourism app",
                    "size": 2324
                },
                {
                    "name": "poems",
                    "size": 10993
                },
                {
                    "name": "presents book ",
                    "size": 335
                },
                {
                    "name": "book war ",
                    "size": 383
                },
                {
                    "name": "crowds ",
                    "size": 874
                },
                {
                    "name": "school news ",
                    "size": 17705
                }
   ]
  },
        {
            "name": "Topic 9",
            "children": [
                {
                    "name": "dublin tomorrow evening ",
                    "size": 8258
                },
                {
                    "name": "yeats2015 sunday ",
                    "size": 10001
                },
                {
                    "name": "see yeats2015 part",
                    "size": 8217
                },
                {
                    "name": "kids day ",
                    "size": 12555
                },
                {
                    "name": "week fleadh",
                    "size": 2324
                },
                {
                    "name": "need uhc ",
                    "size": 10993
                },
                {
                    "name": "thank",
                    "size": 335
                },
                {
                    "name": "evening bankinginquiry",
                    "size": 383
                },
                {
                    "name": "perfect day ",
                    "size": 874
                },
                {
                    "name": "world health",
                    "size": 17705
                }
   ]
  },
        {
            "name": "Topic 10",
            "children": [
                {
                    "name": "month starts tomorrow",
                    "size": 8258
                },
                {
                    "name": "sunday times ",
                    "size": 10001
                },
                {
                    "name": "take place  ",
                    "size": 8217
                },
                {
                    "name": "wildatlanticway",
                    "size": 12555
                },
                {
                    "name": "time october ",
                    "size": 2324
                },
                {
                    "name": "look set",
                    "size": 10993
                },
                {
                    "name": "media ",
                    "size": 335
                },
                {
                    "name": "tourism ",
                    "size": 383
                },
                {
                    "name": "death",
                    "size": 874
                },
                {
                    "name": "visit",
                    "size": 17705
                }
   ]
  }
 ]
}